MANIFEST.in
README.rst
setup.py
twilio_with_thinq/__init__.py
twilio_with_thinq.egg-info/PKG-INFO
twilio_with_thinq.egg-info/SOURCES.txt
twilio_with_thinq.egg-info/dependency_links.txt
twilio_with_thinq.egg-info/not-zip-safe
twilio_with_thinq.egg-info/requires.txt
twilio_with_thinq.egg-info/top_level.txt